mcp_ghost/__init__.py
mcp_ghost/core.py
mcp_ghost/providers/__init__.py
mcp_ghost/providers/anthropic_client.py
mcp_ghost/providers/base.py
mcp_ghost/providers/client_factory.py
mcp_ghost/providers/gemini_client.py
mcp_ghost/providers/openai_client.py
mcp_ghost/providers/openai_style_mixin.py
mcp_ghost/tools/__init__.py
mcp_ghost/tools/adapter.py
mcp_ghost/tools/formatter.py
mcp_ghost/tools/models.py
mcp_ghost/utils/__init__.py
mcp_ghost/utils/prompt_generator.py
mcp_ghost-0.1.0.dist-info/LICENSE
mcp_ghost-0.1.0.dist-info/METADATA
mcp_ghost-0.1.0.dist-info/WHEEL
mcp_ghost-0.1.0.dist-info/top_level.txt
mcp_ghost-0.1.0.dist-info/RECORD
