Metadata-Version: 2.2
Name: mcp-ghost
Version: 0.1.0
Summary: Intelligent MCP tool orchestration library with Claude Desktop-level capabilities
Author-email: June Kim <kim.june.01@gmail.com>
License: MIT
Keywords: mcp,llm,tool-orchestration,ai,automation,claude,openai,gemini
Classifier: Development Status :: 3 - Alpha
Classifier: Intended Audience :: Developers
Classifier: Programming Language :: Python :: 3
Classifier: Programming Language :: Python :: 3.11
Classifier: Programming Language :: Python :: 3.12
Requires-Python: >=3.11
License-File: LICENSE
Requires-Dist: mcp>=1.5.0
Requires-Dist: openai>=1.55.3
Requires-Dist: anthropic>=0.51.0
Requires-Dist: google-genai>=1.15.0
Requires-Dist: python-dotenv>=1.0.1
Requires-Dist: pydantic>=2.10.2
Provides-Extra: dev
Requires-Dist: pytest>=7.0.0; extra == "dev"
Requires-Dist: pytest-asyncio>=0.25.3; extra == "dev"
Requires-Dist: pytest-mock>=3.0.0; extra == "dev"
Requires-Dist: black>=23.0.0; extra == "dev"
Requires-Dist: ruff>=0.1.0; extra == "dev"
Provides-Extra: testing
Requires-Dist: respx>=0.20.0; extra == "testing"
Requires-Dist: httpx>=0.25.0; extra == "testing"
